modulex/__init__.py
modulex-1.2.2.dist-info/licenses/LICENSE
modulex-1.2.2.dist-info/METADATA
modulex-1.2.2.dist-info/WHEEL
modulex-1.2.2.dist-info/top_level.txt
modulex-1.2.2.dist-info/RECORD
