Metadata-Version: 2.4
Name: modulex
Version: 1.2.2
Summary: A short description of your module
Author: Bojidar Georgiev
License: GNU GENERAL PUBLIC LICENSE
Requires-Python: >=3.7
License-File: LICENSE
Dynamic: license-file
